{
"companyName": "DefaultCompany",
"productName": "port",
"productVersion": "0.1",
"dataUrl": "Portafolio_003.data.unityweb",
"wasmCodeUrl": "Portafolio_003.wasm.code.unityweb",
"wasmFrameworkUrl": "Portafolio_003.wasm.framework.unityweb",
"graphicsAPI": ["WebGL 2.0"],
"webglContextAttributes": {"preserveDrawingBuffer": false},
"splashScreenStyle": "Dark",
"backgroundColor": "#231F20",
"cacheControl": {"default": "must-revalidate"},
"developmentBuild": false,
"multithreading": false,
"unityVersion": "2019.3.12f1"
}